LICENSE
MANIFEST.in
README.md
setup.py
myprefetch/__init__.py
myprefetch/binlog.py
myprefetch/custom_query_prefetch.py
myprefetch/fake_updates_prefetch.py
myprefetch/mysql.py
myprefetch/readahead.py
myprefetch/rewriters.py
myprefetch.egg-info/PKG-INFO
myprefetch.egg-info/SOURCES.txt
myprefetch.egg-info/dependency_links.txt
myprefetch.egg-info/requires.txt
myprefetch.egg-info/top_level.txt