Metadata-Version: 1.0
Name: myprefetch
Version: 0.1
Summary: MySQL Replication Prefetcher
Home-page: https://github.com/vine/mysql-prefetcher
Author: UNKNOWN
Author-email: UNKNOWN
License: Apache License
